MANIFEST.in
Makefile
custom_script_linear_dwell_time.py
requirements.txt
setup.cfg
setup.py
ui_screenshot.PNG
colosseum_ui/__init__.py
colosseum_ui/colosseum.py
colosseum_ui/constants.py
colosseum_ui/run.py
colosseum_ui/serial_comm.py
colosseum_ui/ui.py
colosseum_ui/ui_screenshot.PNG
colosseum_ui/unit_conversion.py
colosseum_ui/utils.py
colosseum_ui.egg-info/PKG-INFO
colosseum_ui.egg-info/SOURCES.txt
colosseum_ui.egg-info/dependency_links.txt
colosseum_ui.egg-info/entry_points.txt
colosseum_ui.egg-info/not-zip-safe
colosseum_ui.egg-info/requires.txt
colosseum_ui.egg-info/top_level.txt
colosseum_ui/data/angles.txt
colosseum_ui/data/fractioncollector.ui