Metadata-Version: 2.1
Name: colosseum-ui
Version: 0.0.6
Summary: colosseum system - open source fraction collector for laboratories
Home-page: https://github.com/sbooeshaghi/colosseum
Author: Kyung Hoi (Joseph) Min, Yeokyoung (Anne) Kil, A. Sina Booeshaghi
Author-email: phoenixter96@gmail.com, ykil@caltech.edu, abooesha@caltech.edu
Maintainer: Kyung Hoi (Joseph) Min
Maintainer-email: phoenixter96@gmail.com
License: BSD
Platform: UNKNOWN
Classifier: Development Status :: 4 - Beta
Classifier: Environment :: X11 Applications :: Qt
Classifier: Intended Audience :: Science/Research
Classifier: License :: OSI Approved :: BSD License
Classifier: Operating System :: OS Independent
Classifier: Programming Language :: Python :: 3.6
Classifier: Programming Language :: Python :: 3.7
Classifier: Programming Language :: Python :: 3.8
Classifier: Topic :: Scientific/Engineering
Classifier: Topic :: Software Development :: User Interfaces
Classifier: Topic :: System :: Hardware :: Hardware Drivers
Requires-Python: >=3.6
